niles_api_client/__init__.py
niles_api_client/const.py
niles_api_client/util.py
niles_api_client-0.0.5.dist-info/LICENSE
niles_api_client-0.0.5.dist-info/METADATA
niles_api_client-0.0.5.dist-info/WHEEL
niles_api_client-0.0.5.dist-info/top_level.txt
niles_api_client-0.0.5.dist-info/RECORD
