Metadata-Version: 2.1
Name: niles-api-client
Version: 0.0.5
Summary: API client for Niles Household Management
Home-page: https://github.com/niles-household-management/niles-api-client
Author: Markus Ressel
Author-email: mail@markusressel.de
License: AGPLv3+
Platform: UNKNOWN
Classifier: Development Status :: 5 - Production/Stable
Classifier: License :: OSI Approved :: GNU Affero General Public License v3 or later (AGPLv3+)
Classifier: Programming Language :: Python :: 3
Classifier: Programming Language :: Python :: 3.6
Classifier: Programming Language :: Python :: 3.7
Classifier: Programming Language :: Python :: 3.8
Requires-Dist: parsedatetime
Requires-Dist: websockets
